turso_python/__init__.py
turso_python/advanced_queries.py
turso_python/async_connection.py
turso_python/async_crud.py
turso_python/batch.py
turso_python/connection.py
turso_python/crud.py
turso_python/exceptions.py
turso_python/logger.py
turso_python/response_parser.py
turso_python/result.py
turso_python/schema_validator.py
turso_python/turso_vector.py
turso_python-1.8.dist-info/METADATA
turso_python-1.8.dist-info/WHEEL
turso_python-1.8.dist-info/licenses/LICENSE
turso_python-1.8.dist-info/RECORD
