Metadata-Version: 2.4
Name: turso-python
Version: 1.8
Summary: A Python client for Turso/libsql HTTP API with sync and async support
Author-email: Marcus Peterson <marcus.peterson.tech@gmail.com>
Maintainer-email: Srikanth <srikanth.gokr@gmail.com>
License: Apache-2.0
License-File: LICENSE
Keywords: aiohttp,async,client,http,libsql,msgspec,sqlite,turso
Classifier: License :: OSI Approved :: Apache Software License
Classifier: Operating System :: OS Independent
Classifier: Programming Language :: Python :: 3
Requires-Python: >=3.10
Requires-Dist: aiohttp
Requires-Dist: anyio
Requires-Dist: msgspec
Requires-Dist: requests
Provides-Extra: dev
Requires-Dist: aioresponses; extra == 'dev'
Requires-Dist: pytest; extra == 'dev'
Requires-Dist: pytest-asyncio; extra == 'dev'
Requires-Dist: requests-mock; extra == 'dev'
Requires-Dist: ruff; extra == 'dev'
Requires-Dist: types-requests; extra == 'dev'
